CHANGELOG
COPYRIGHT
LICENSE
MANIFEST.in
MIGRATION
Makefile
requirements.txt
setup.py
Nereid.egg-info/PKG-INFO
Nereid.egg-info/SOURCES.txt
Nereid.egg-info/dependency_links.txt
Nereid.egg-info/not-zip-safe
Nereid.egg-info/requires.txt
Nereid.egg-info/top_level.txt
docs/Makefile
docs/advanced_foreword.rst
docs/api.rst
docs/conf.py
docs/contents.rst.inc
docs/foreword.rst
docs/index.rst
docs/installation.rst
docs/license.rst
docs/make.bat
docs/quickstart.rst
docs/tryton_module_api.rst
docs/tutorial.rst
docs/versionmanagement.rst
nereid/__init__.py
nereid/application.py
nereid/backend.py
nereid/caching.py
nereid/config.py
nereid/ctx.py
nereid/globals.py
nereid/helpers.py
nereid/logging.py
nereid/session.py
nereid/sessions.py
nereid/signals.py
nereid/templating.py
nereid/testing.py
nereid/wrappers.py
nereid/contrib/__init__.py
nereid/contrib/locale.py
nereid/contrib/pagination.py
nereid/contrib/sitemap.py
tests/__init__.py