Metadata-Version: 1.0
Name: Nereid
Version: 2.8.0.2
Summary: Tryton - Web Framework
Home-page: http://nereid.openlabs.co.in/docs/
Author: Openlabs Technologies & Consulting (P) Limited
Author-email: info@openlabs.co.in
License: GPLv3
Platform: any
Classifier: Development Status :: 4 - Beta
Classifier: Environment :: Web Environment
Classifier: Intended Audience :: Developers
Classifier: License :: OSI Approved :: GNU General Public License v3 (GPLv3)
Classifier: Operating System :: OS Independent
Classifier: Programming Language :: Python
Classifier: Framework :: Tryton
Classifier: Topic :: Internet :: WWW/HTTP :: Dynamic Content
Classifier: Topic :: Software Development :: Libraries :: Python Modules
